lu_semver/__init__.py
lu_semver/__main__.py
lu_semver/__version__.py
lu_semver/git.py
lu_semver/misc.py
lu_semver/scm.py
lu_semver-4.0.2.dist-info/LICENSE
lu_semver-4.0.2.dist-info/METADATA
lu_semver-4.0.2.dist-info/WHEEL
lu_semver-4.0.2.dist-info/entry_points.txt
lu_semver-4.0.2.dist-info/top_level.txt
lu_semver-4.0.2.dist-info/RECORD
