Metadata-Version: 2.1
Name: lu-semver
Version: 4.0.2
Summary: print semantic version for git projects
Home-page: https://gitlab.com/aanatoly/semver-tool
Author: Anatoly Asviyan
Author-email: anatoly@gmail.com
License: GPLv2
Platform: UNKNOWN
Classifier: Development Status :: 4 - Beta
Classifier: Environment :: Console
Classifier: Intended Audience :: Developers
Classifier: License :: OSI Approved :: GNU General Public License v2 (GPLv2)
Classifier: Operating System :: POSIX
Classifier: Programming Language :: Python :: 3
Classifier: Topic :: Software Development
Provides-Extra: dev
Requires-Dist: twine ; extra == 'dev'
Requires-Dist: tox ; extra == 'dev'
